<?xml version="1.0" ?>
<container xmlns="http://symfony.com/schema/dic/services"
           xmlns:xsi="http://www.w3.org/2001/XMLSchema-instance"
           xsi:schemaLocation="http://symfony.com/schema/dic/services http://symfony.com/schema/dic/services/services-1.0.xsd">


    <services>
        <!-- A: event handler interface declaration (required) -->
        <service id="Boxalino\DataIntegration\Service\InstantUpdateHandlerInterface" class="Boxalino\DataIntegration\Service\InstantUpdateHandler">
            <argument type="service" id="boxalino.di.configurator"/>
            <argument type="service" id="Boxalino\DataIntegrationDoc\Service\GcpClientInterface"/>
            <argument type="service" id="Boxalino\DataIntegrationDoc\Service\Integration\IntegrationHandlerInterface"/>
        </service>

        <!-- B: uses the event handler from A -->
        <service id="Boxalino\DataIntegration\Service\InstantUpdate\ProductSubscriber">
            <argument type="service" id="Boxalino\DataIntegration\Service\InstantUpdateHandlerInterface"/>
            <tag name="kernel.event_subscriber"/>
        </service>

        <!-- X: doc_product generator for what product attributes are exported on instant update with the use of the handlers -->
        <!-- relevant updates can be applied to: price, pricing, stock, entity-->
        <service id="Boxalino\DataIntegrationDoc\Service\Integration\DocProductHandlerInterface"
                 class="Boxalino\DataIntegration\Service\InstantUpdate\Document\Product\DocHandler">
            <argument type="service" id="monolog.logger.boxalino-di"/>
            <call method="addHandler">
                <argument type="service" id="boxalino.di.instant.attribute.category"/>
            </call>
            <call method="addHandler">
                <argument type="service" id="boxalino.di.instant.attribute.entity"/>
            </call>
            <call method="addHandler">
                <argument type="service" id="boxalino.di.instant.attribute.price"/>
            </call>
            <call method="addHandler">
                <argument type="service" id="boxalino.di.instant.attribute.pricing"/>
            </call>
            <call method="addHandler">
                <argument type="service" id="boxalino.di.instant.attribute.stock"/>
            </call>
            <call method="addHandler">
                <argument type="service" id="boxalino.di.instant.attribute.translation"/>
            </call>
            <call method="addHandler">
                <argument type="service" id="boxalino.di.instant.attribute.visibility"/>
            </call>
        </service>

        <!-- Y: doc_languages generator -->
        <service id="Boxalino\DataIntegrationDoc\Service\Integration\DocLanguagesHandlerInterface"
                 class="Boxalino\DataIntegration\Service\InstantUpdate\Document\Language\DocHandler">
        </service>

        <!-- Z: doc_attribute_values generator (required for category synchronization) -->
        <service id="Boxalino\DataIntegrationDoc\Service\Integration\DocAttributeValuesHandlerInterface"
                 class="Boxalino\DataIntegration\Service\InstantUpdate\Document\Attribute\Values\DocHandler">
            <argument type="service" id="monolog.logger.boxalino-di"/>
            <call method="addHandler">
                <argument type="service" id="boxalino.di.instant.values.category"/>
            </call>
        </service>

        <!-- W: instant-update integration handler - generates each file tyle (handler) -->
        <service id="Boxalino\DataIntegrationDoc\Service\Integration\IntegrationHandlerInterface"
                 class="Boxalino\DataIntegration\Service\InstantUpdate\Document\DocHandler">
            <call method="addHandler">
                <argument type="service" id="Boxalino\DataIntegrationDoc\Service\Integration\DocProductHandlerInterface"/>
            </call>
            <call method="addHandler">
                <argument type="service" id="Boxalino\DataIntegrationDoc\Service\Integration\DocLanguagesHandlerInterface"/>
            </call>
            <call method="addHandler">
                <argument type="service" id="Boxalino\DataIntegrationDoc\Service\Integration\DocAttributeValuesHandlerInterface"/>
            </call>
        </service>

        <!-- F: localized properties Doc Attribute Handler -->
        <service id="boxalino.di.instant.attribute.translation" class="Boxalino\DataIntegration\Service\InstantUpdate\Document\Product\Attribute\Translation">
            <argument type="service" id="Doctrine\DBAL\Connection"/>
            <argument type="service" id="boxalino.di.util.localized"/>
            <call method="addPropertyNameDocAttributeMapping">
                <argument>name</argument>
                <argument>title</argument>
            </call>
        </service>

        <!-- G: Visibility Doc Attribute Handler -->
        <service id="boxalino.di.instant.attribute.visibility" class="Boxalino\DataIntegration\Service\InstantUpdate\Document\Product\Attribute\Visibility">
            <argument type="service" id="Doctrine\DBAL\Connection"/>
            <call method="addPropertyNameDocAttributeMapping">
                <argument>visibility</argument>
            </call>
        </service>

        <!-- H: SKU Price Attribute Handler -->
        <service id="boxalino.di.instant.attribute.price" class="Boxalino\DataIntegration\Service\InstantUpdate\Document\Product\Attribute\Price">
            <argument type="service" id="Doctrine\DBAL\Connection"/>
            <call method="addPropertyNameDocAttributeMapping">
                <argument>price</argument>
            </call>
        </service>

        <!-- I: Product Line / Product Groups Pricing Attribute Handler -->
        <service id="boxalino.di.instant.attribute.pricing" class="Boxalino\DataIntegration\Service\InstantUpdate\Document\Product\Attribute\Pricing">
            <argument type="service" id="Doctrine\DBAL\Connection"/>
            <call method="addPropertyNameDocAttributeMapping">
                <argument>pricing</argument>
            </call>
        </service>

        <!-- J: Stock Attribute Handler -->
        <service id="boxalino.di.instant.attribute.stock" class="Boxalino\DataIntegration\Service\InstantUpdate\Document\Product\Attribute\Stock">
            <argument type="service" id="Doctrine\DBAL\Connection"/>
            <call method="addPropertyNameDocAttributeMapping">
                <argument>stock</argument>
            </call>
        </service>

        <!-- K: Categorization Attribute Handler -->
        <service id="boxalino.di.instant.attribute.category" class="Boxalino\DataIntegration\Service\InstantUpdate\Document\Product\Attribute\Category">
            <argument type="service" id="Doctrine\DBAL\Connection"/>
            <argument type="service" id="boxalino.di.instant.values.category"/>
            <call method="addPropertyNameDocAttributeMapping">
                <argument>categories</argument>
            </call>
        </service>

        <!-- L: Generic product attributes from product table Attribute Handler -->
        <service id="boxalino.di.instant.attribute.entity" class="Boxalino\DataIntegration\Service\InstantUpdate\Document\Product\Attribute\Entity">
            <argument type="service" id="Doctrine\DBAL\Connection"/>
            <call method="addPropertyNameDocAttributeMapping">
                <argument>internal_id</argument>
            </call>
            <call method="addPropertyNameDocAttributeMapping">
                <argument>sku</argument>
            </call>
            <call method="addPropertyNameDocAttributeMapping">
                <argument>ean</argument>
            </call>
            <call method="addPropertyNameDocAttributeMapping">
                <argument>last_update</argument>
            </call>
            <call method="addPropertyNameDocAttributeMapping">
                <argument>status</argument>
            </call>
            <call method="addPropertyNameDocAttributeMapping">
                <argument>rating_average</argument>
                <argument>numeric_attributes</argument>
            </call>
            <call method="addPropertyNameDocAttributeMapping">
                <argument>is_closeout</argument>
                <argument>numeric_attributes</argument>
            </call>
            <call method="addPropertyNameDocAttributeMapping">
                <argument>release_date</argument>
                <argument>datetime_attributes</argument>
            </call>
            <call method="addSchemaDefinition">
                <argument>status</argument>
                <argument>Boxalino\DataIntegrationDoc\Service\Doc\Schema\Status</argument>
            </call>
            <call method="addSchemaDefinition">
                <argument>string_attributes</argument>
                <argument>Boxalino\DataIntegrationDoc\Service\Doc\Schema\Typed\StringAttribute</argument>
            </call>
            <call method="addSchemaDefinition">
                <argument>numeric_attributes</argument>
                <argument>Boxalino\DataIntegrationDoc\Service\Doc\Schema\Typed\NumericAttribute</argument>
            </call>
            <call method="addSchemaDefinition">
                <argument>datetime_attributes</argument>
                <argument>Boxalino\DataIntegrationDoc\Service\Doc\Schema\Typed\DatetimeAttribute</argument>
            </call>
        </service>

        <!-- M: Attribute Handler for the category values (hierarchical) -->
        <service id="boxalino.di.instant.values.category" class="Boxalino\DataIntegration\Service\InstantUpdate\Document\Attribute\Values\Category">
            <argument type="service" id="Doctrine\DBAL\Connection"/>
            <argument type="service" id="boxalino.di.util.localized"/>
        </service>

    </services>
</container>
